datatxt.py
setup.py
dataTXT.egg-info/PKG-INFO
dataTXT.egg-info/SOURCES.txt
dataTXT.egg-info/dependency_links.txt
dataTXT.egg-info/requires.txt
dataTXT.egg-info/top_level.txt