Metadata-Version: 1.1
Name: dataTXT
Version: 0.1
Summary: python interface for SpazioDati's dataTXT and DBpedia
Home-page: https://github.com/SpazioDati/python-datatxt
Author: Marco Amadori
Author-email: amadori@spaziodati.eu
License: BSD
Platform: UNKNOWN
Classifier: Development Status :: 2 - Pre-Alpha
Classifier: Environment :: Console
Classifier: Intended Audience :: Developers
Classifier: License :: OSI Approved :: BSD License
Classifier: Operating System :: MacOS :: MacOS X
Classifier: Operating System :: POSIX
Classifier: Natural Language :: Italian
Classifier: Natural Language :: English
Classifier: Programming Language :: Python
Classifier: Topic :: Database
Classifier: Topic :: Software Development :: Libraries :: Python Modules
Classifier: Topic :: Text Processing :: Indexing
